basicwrangler/__init__.py
basicwrangler/basicwrangler.py
basicwrangler/version.py
basicwrangler/common/__init__.py
basicwrangler/common/constants.py
basicwrangler/common/functions.py
basicwrangler/convert/__init__.py
basicwrangler/convert/helpers.py
basicwrangler/convert/label.py
basicwrangler/defs/__init__.py
basicwrangler/defs/abbrevs.yaml
basicwrangler/defs/basdefs.py
basicwrangler/defs/basdefs.yaml
basicwrangler/icon/__init__.py
basicwrangler/icon/config_icon.png
basicwrangler/icon/program_icon.ico
basicwrangler/icon/program_icon.png
basicwrangler/lex/__init__.py
basicwrangler/lex/genlex.py
basicwrangler/lex/lexer.py
basicwrangler/lex/rules.yaml
basicwrangler/renum/__init__.py
basicwrangler/renum/renumber.py
basic_wrangler-0.7.1.dist-info/LICENSE
basic_wrangler-0.7.1.dist-info/METADATA
basic_wrangler-0.7.1.dist-info/WHEEL
basic_wrangler-0.7.1.dist-info/entry_points.txt
basic_wrangler-0.7.1.dist-info/top_level.txt
basic_wrangler-0.7.1.dist-info/RECORD
