Metadata-Version: 2.1
Name: basic-wrangler
Version: 0.7.1
Summary: A BASIC program listing line renumberer/cruncher (aka, a minifier).
Home-page: https://github.com/pahandav/basic-wrangler
Author: pahandav
Author-email: 34494459+pahandav@users.noreply.github.com
License: UNKNOWN
Project-URL: Documentation, https://github.com/pahandav/basic-wrangler/blob/master/docs/Manual.asc
Project-URL: Source, https://github.com/pahandav/basic-wrangler
Project-URL: Issue Tracker, https://github.com/pahandav/basic-wrangler/issues
Project-URL: Release Thread, https://atariage.com/forums/topic/297649-basic-wrangler-a-line-cruncherrenumberer/
Project-URL: Blog, https://oldschoolbasic.blogspot.com/
Keywords: basic cruncher development
Platform: UNKNOWN
Classifier: Development Status :: 4 - Beta
Classifier: Programming Language :: Python :: 3
Classifier: License :: OSI Approved :: GNU General Public License v3 (GPLv3)
Classifier: Operating System :: OS Independent
Classifier: Intended Audience :: Developers
Classifier: Programming Language :: Basic
Classifier: Topic :: Software Development :: Build Tools
Classifier: Topic :: Software Development :: Pre-processors
Requires-Python: >=3.6
Requires-Dist: pyperclip
Requires-Dist: Gooey
Requires-Dist: PyYAML
Requires-Dist: loguru
